MANIFEST.in
README.rst
setup.py
FEMsolverPDE.egg-info/PKG-INFO
FEMsolverPDE.egg-info/SOURCES.txt
FEMsolverPDE.egg-info/dependency_links.txt
FEMsolverPDE.egg-info/top_level.txt
mesh/__init__.py
mesh/mesh.py
mesh/mesh_1d.py
mesh/mesh_2d.py
solver/FEMsolverPDE1d.py
solver/FEMsolverPDE2d.py
solver/__init__.py