Metadata-Version: 1.1
Name: FEMsolverPDE
Version: 1.1
Summary: Solve 1D and 2D PDE by finite elements method.
Home-page: https://github.com/un1t/django-cleanup
Author: Andrei Chertkov
Author-email: andrey.mipt@mail.ru
License: MIT License
Download-URL: https://github.com/un1t/django-cleanup/tarball/master
Keywords: finite element,pde,pde solver
Platform: UNKNOWN
Classifier: Environment :: Web Environment
Classifier: Intended Audience :: Developers
Classifier: Programming Language :: Python
Requires: python (>= 2.5)
